Metadata-Version: 2.1
Name: py-mathjax
Version: 2.7.6
Summary: Installs mathjax conda package in pip and conda.
Home-page: https://github.com/kiwi0fruit/py-mathjax
Author: kiwi0fruit
Author-email: peter.zagubisalo@gmail.com
License: Apache License 2.0
Platform: UNKNOWN
Classifier: Development Status :: 3 - Alpha
Classifier: Topic :: Software Development :: Build Tools
Classifier: Programming Language :: Python :: 3
Classifier: Programming Language :: Python :: 3.6
Requires-Python: >=3.6
